brambox/__init__.py
brambox/_version.py
brambox/_imports.py
brambox/util/_log.py
brambox/util/_pd.py
brambox/util/_morton.cpp
brambox/util/__init__.py
brambox/util/_dualgroupby.py
brambox/util/_visual.py
brambox/util/_morton.cpython-37m-x86_64-linux-gnu.so
brambox/util/_sparsematrix.cpp
brambox/util/_boundingbox.py
brambox/util/_sparsematrix.cpython-37m-x86_64-linux-gnu.so
brambox/stat/__init__.py
brambox/stat/_lrp.py
brambox/stat/_curve.py
brambox/stat/_pr.py
brambox/stat/coordinates.cpp
brambox/stat/_matchboxes.cpp
brambox/stat/_mot.py
brambox/stat/_matchboxes.cpython-37m-x86_64-linux-gnu.so
brambox/stat/_mr_fppi.py
brambox/stat/coordinates.cpython-37m-x86_64-linux-gnu.so
brambox/eval/_tide.py
brambox/eval/__init__.py
brambox/eval/_coco.py
brambox/eval/_tidal.py
brambox/eval/_cache.py
brambox/io/__init__.py
brambox/io/_util.py
brambox/io/_io.py
brambox/io/parser/__init__.py
brambox/io/parser/_formats.py
brambox/io/parser/_parser.py
brambox/io/parser/generic/_pandas.py
brambox/io/parser/generic/__init__.py
brambox/io/parser/annotation/_kitti.py
brambox/io/parser/annotation/__init__.py
brambox/io/parser/annotation/_dota.py
brambox/io/parser/annotation/_cvat_image.py
brambox/io/parser/annotation/_darknet.py
brambox/io/parser/annotation/_coco.py
brambox/io/parser/annotation/_cvat_video.py
brambox/io/parser/annotation/_vatic.py
brambox/io/parser/annotation/_hrsc.py
brambox/io/parser/annotation/_pascalvoc.py
brambox/io/parser/annotation/_mot.py
brambox/io/parser/annotation/_dollar.py
brambox/io/parser/annotation/_cvc.py
brambox/io/parser/annotation/_yaml.py
brambox/io/parser/detection/__init__.py
brambox/io/parser/detection/_coco.py
brambox/io/parser/detection/_pascalvoc.py
brambox/io/parser/detection/_mot.py
brambox/io/parser/detection/_dollar.py
brambox/io/parser/detection/_erti.py
brambox/io/parser/detection/_yaml.py
brambox-5.0.0.dist-info/LICENSE
brambox-5.0.0.dist-info/WHEEL
brambox-5.0.0.dist-info/top_level.txt
brambox-5.0.0.dist-info/RECORD
brambox-5.0.0.dist-info/METADATA
