Metadata-Version: 2.1
Name: brambox
Version: 5.0.0
Summary: Basic Requisites for Algorithms on iMages toolBOX
Author: EAVISE, Tanguy Ophoff, Maarten Vandersteegen
License: Copyright 2017 EAVISE
Project-URL: Homepage, https://gitlab.com/EAVISE/brambox
Project-URL: Documentation, https://eavise.gitlab.io/brambox
Project-URL: Repository, https://gitlab.com/EAVISE/brambox
Requires-Python: >=3.7
Provides-Extra: segment
Provides-Extra: segmentation
License-File: LICENSE
